cobo_cli/__init__.py
cobo_cli/apps_commands.py
cobo_cli/commands.py
cobo_cli/config_commands.py
cobo_cli/constants.py
cobo_cli/keys_commands.py
cobo_cli/login_commands.py
cobo_cli/client/__init__.py
cobo_cli/client/portal_client.py
cobo_cli/data/__init__.py
cobo_cli/data/constants.py
cobo_cli/data/enums.py
cobo_cli/data/objects.py
cobo_cli/managers/OrgTokenManager.py
cobo_cli/managers/UserTokenManager.py
cobo_cli/managers/__init__.py
cobo_cli/managers/env_manager.py
cobo_cli/managers/keys_manager.py
cobo_cli/managers/tests/__init__.py
cobo_cli/managers/tests/test_keys_manager.py
cobo_cli/tests/__init__.py
cobo_cli/tests/test_apps_commands.py
cobo_cli/tests/test_config_commands.py
cobo_cli/tests/test_keys_commands.py
cobo_cli/tests/test_login_commands.py
cobo_cli/toolkit/__init__.py
cobo_cli/toolkit/signer.py
cobo_cli/toolkit/tests/__init__.py
cobo_cli/toolkit/tests/test_signer.py
cobo_cli/utils/__init__.py
cobo_cli/utils/common.py
cobo_cli/utils/portal_client.py
cobo-0.0.1.dist-info/METADATA
cobo-0.0.1.dist-info/WHEEL
cobo-0.0.1.dist-info/entry_points.txt
cobo-0.0.1.dist-info/top_level.txt
cobo-0.0.1.dist-info/RECORD
